contentspark/__init__.py
contentspark/core.py
contentspark-0.1.2.dist-info/licenses/LICENSE
contentspark-0.1.2.dist-info/METADATA
contentspark-0.1.2.dist-info/WHEEL
contentspark-0.1.2.dist-info/top_level.txt
contentspark-0.1.2.dist-info/RECORD
